{
  "title": "พวกผู้ชายใจโลเล ใครได้ไปก็มีแต่ความทุกข์",
  "thumbnail": "https://scontent.fbmv1-1.fna.fbcdn.net/v/t15.5256-10/442695333_811249760727246_2714171217414131168_n.jpg?stp=dst-jpg_s960x960_tt6&_nc_cat=105&ccb=1-7&_nc_sid=be8305&_nc_ohc=nB0Ers6Y600Q7kNvwEuq76h&_nc_oc=Admz25THLyOutwUaPQkmG6nlEjdCHHkS01xHRv8iaBRAAGyQ4gI-pDAeJ0J1WRIh120&_nc_zt=23&_nc_ht=scontent.fbmv1-1.fna&_nc_gid=uXIcM76I8rQjmb9Pnnt86A&oh=00_AftVZyhj4mmLO9s8IS5W9XOENh8iO3z2g6OfHnmD2LykIw&oe=69A5C0AB",
  "success": true,
  "error": null,
  "url": "https://www.facebook.com/reel/2152829721759402/"
}