{
  "title": "ผู้หญิงไม่รักดี ชอบเป็นเมียน้อยมากกว่าเป็นเมียหลวง",
  "thumbnail": "https://scontent.fbmv1-1.fna.fbcdn.net/v/t15.5256-10/451698114_1023271462063290_7041189787892170961_n.jpg?stp=dst-jpg_s960x960_tt6&_nc_cat=111&ccb=1-7&_nc_sid=be8305&_nc_ohc=kGuTBQIuVMoQ7kNvwEPtv_z&_nc_oc=AdkjljIDBGhCxD9_tyDIYyvH3fg7msE9BLJoqHU7ZVVc8KQqtnAEm_--ettbcmrO53M&_nc_zt=23&_nc_ht=scontent.fbmv1-1.fna&_nc_gid=uHVMHby5M-AIDE1nupYoxw&oh=00_AfuS8-f2fg-MJAHk7iEI8P0-Pu3aiYxMWwqVWI5A-f8Ckg&oe=69A5DC57",
  "success": true,
  "error": null,
  "url": "https://www.facebook.com/reel/457588540468346/"
}