{
  "title": "ถ้าผู้ชายที่เขารักเรา เขาจะไม่ยอมให้ผู้หญิงลำบาก",
  "thumbnail": "https://scontent.fbmv1-1.fna.fbcdn.net/v/t15.5256-10/438191400_998078301966595_5525178501989882851_n.jpg?stp=dst-jpg_s960x960_tt6&_nc_cat=110&ccb=1-7&_nc_sid=be8305&_nc_ohc=GA0EdvyTFtYQ7kNvwEYNjgs&_nc_oc=AdmfvS9LjUBHY6B0Fj0OQyDZ55yFeRHxL9tG7ZIm6rfbQrmDBHwxBCEJUQv4YM_ujjg&_nc_zt=23&_nc_ht=scontent.fbmv1-1.fna&_nc_gid=AqDYy-JJGXnklMir82oSPQ&oh=00_Aftb39Ei5lLuiNHN51aap8vrmxUjdVh4Kk8pmDqQoX-apA&oe=69A5CCA9",
  "success": true,
  "error": null,
  "url": "https://www.facebook.com/reel/674793531479220/"
}